garf/community/experimental/media_tagging/__init__.py
garf/community/experimental/media_tagging/api_clients.py
garf/community/experimental/media_tagging/query_editor.py
garf/community/experimental/media_tagging/report_fetcher.py
garf/community/experimental/media_tagging/simulator.py
garf_media_tagging-0.0.2.dist-info/METADATA
garf_media_tagging-0.0.2.dist-info/WHEEL
garf_media_tagging-0.0.2.dist-info/entry_points.txt
garf_media_tagging-0.0.2.dist-info/top_level.txt
garf_media_tagging-0.0.2.dist-info/RECORD
