Metadata-Version: 2.4
Name: garf-media-tagging
Version: 0.0.2
Summary: Garf implementation for media tagger
Author-email: Andrei Markin <amarkin@google.com>, "Google Inc. (gTech gPS CSE team)" <no-reply@google.com>
License: Apache 2.0
Classifier: Development Status :: 4 - Beta
Classifier: Programming Language :: Python
Requires-Python: >=3.9
Requires-Dist: garf-core>=1.0.0
Requires-Dist: garf-io>=1.0.0
Requires-Dist: media-tagging[server]
Provides-Extra: test
Requires-Dist: pytest; extra == "test"
Requires-Dist: pytest-cov; extra == "test"
Requires-Dist: python-dotenv; extra == "test"
